cisco_netsim_by_KARPAGAM/__init__.py
cisco_netsim_by_KARPAGAM/main.py
cisco_network_simulation_by_karpagam-1.0.6.dist-info/METADATA
cisco_network_simulation_by_karpagam-1.0.6.dist-info/WHEEL
cisco_network_simulation_by_karpagam-1.0.6.dist-info/entry_points.txt
cisco_network_simulation_by_karpagam-1.0.6.dist-info/top_level.txt
cisco_network_simulation_by_karpagam-1.0.6.dist-info/RECORD
