Metadata-Version: 2.4
Name: cisco-network-simulation-by-karpagam
Version: 1.0.6
Summary: 🌐 Professional Cisco Network Analysis & Simulation Toolkit by Karpagam
Author: Karpagam
Author-email: karpagam@college.edu
Keywords: cisco,network,simulation,analysis,karpagam
Classifier: Development Status :: 5 - Production/Stable
Classifier: Intended Audience :: Information Technology
Classifier: Topic :: System :: Networking
Classifier: Programming Language :: Python :: 3
Classifier: Programming Language :: Python :: 3.8
Classifier: Programming Language :: Python :: 3.9
Classifier: Programming Language :: Python :: 3.10
Classifier: Programming Language :: Python :: 3.11
Classifier: Programming Language :: Python :: 3.12
Classifier: Programming Language :: Python :: 3.13
Classifier: Operating System :: OS Independent
Requires-Python: >=3.8
Requires-Dist: matplotlib>=3.5.0
Requires-Dist: networkx>=2.8.0
Requires-Dist: simpy>=4.0.0
Requires-Dist: pandas>=1.4.0
Requires-Dist: numpy>=1.21.0
Dynamic: author
Dynamic: author-email
Dynamic: classifier
Dynamic: description
Dynamic: description-content-type
Dynamic: keywords
Dynamic: requires-dist
Dynamic: requires-python
Dynamic: summary
